nomadix_api/__init__.py
nomadix_api/api.py
nomadix_api/utils/__init__.py
nomadix_api/utils/decorators.py
nomadix_api-0.0.1.dist-info/METADATA
nomadix_api-0.0.1.dist-info/WHEEL
nomadix_api-0.0.1.dist-info/top_level.txt
nomadix_api-0.0.1.dist-info/RECORD
