Metadata-Version: 2.1
Name: nomadix-api
Version: 0.0.1
Summary: UNKNOWN
Author: Nelson Fonseca
Author-email: ioannova@hotmail.com
License: UNKNOWN
Platform: UNKNOWN
Classifier: Development Status :: 3 - Alpha
Classifier: Intended Audience :: Information Technology
Classifier: Operating System :: OS Independent
Classifier: Programming Language :: Python :: 3
Classifier: Topic :: Software Development :: Libraries :: Python Modules
Classifier: Topic :: Utilities
Requires-Dist: requests (<3,>=2.23.0)
